<cdcs>
  <area_0>
    <point_x>[427141.68707186 427154.61872341 427153.03062585 427140.55271646]</point_x>
    <point_y>[3382059.51794598 3382055.97152509 3382052.15230259 3382056.10792589]</point_y>
  </area_0>
  <area_1>
    <point_x>[427140.55271646 427153.25749693 427152.57688369 427138.9646189 ]</point_x>
    <point_y>[3382056.10792589 3382052.15230259 3382048.19667928 3382052.28870339]</point_y>
  </area_1>
  <area_2>
    <point_x>[427138.9646189  427152.12314153 427151.66939937 427136.92277918]</point_x>
    <point_y>[3382052.28870339 3382048.33308009 3382044.92306    3382049.01508411]</point_y>
  </area_2>
  <area_3>
    <point_x>[427136.6959081  427135.10781055 427150.30817289 427151.44252829]</point_x>
    <point_y>[3382049.01508411 3382045.19586161 3382040.69463509 3382044.65025839]</point_y>
  </area_3>
</cdcs>